pyit600/__init__.py
pyit600/__version__.py
pyit600/const.py
pyit600/encryptor.py
pyit600/exceptions.py
pyit600/gateway.py
pyit600/gateway_singleton.py
pyit600/models.py
pyit600-0.5.1.dist-info/LICENSE
pyit600-0.5.1.dist-info/METADATA
pyit600-0.5.1.dist-info/WHEEL
pyit600-0.5.1.dist-info/top_level.txt
pyit600-0.5.1.dist-info/RECORD
