Metadata-Version: 2.1
Name: pyit600
Version: 0.5.1
Summary: Asynchronous Python client for Salus IT600 devices
Home-page: https://github.com/jvitkauskas/pyit600
Author: Julius Vitkauskas
Author-email: zadintuvas@gmail.com
License: MIT license
Keywords: salus,it600,api,async,client
Classifier: Development Status :: 3 - Alpha
Classifier: Framework :: AsyncIO
Classifier: Programming Language :: Python :: 3.7
Classifier: Topic :: Scientific/Engineering :: Interface Engine/Protocol Translator
Requires-Python: >=3.7
License-File: LICENSE
Requires-Dist: aiohttp (>=3.8.1)
Requires-Dist: cryptography (>=38.0.1)
